{
  "id": "pkp/9",
  "title": "3.  9. Gizi",
  "description": "Pelayanan gizi dilakukan sesuai dengan kebutuhan pasien dan sesuai dengan ketentuan peraturan perundang-undangan, pasien berperan serta dalam perencanaan dan seleksi makanan.",
  "source": "@site/docs/04-pkp/9.md",
  "sourceDirName": "04-pkp",
  "slug": "/pkp/9",
  "permalink": "/docs/pkp/9",
  "draft": false,
  "unlisted": false,
  "editUrl": "https://github.com/facebook/docusaurus/tree/main/packages/create-docusaurus/templates/shared/docs/04-pkp/9.md",
  "tags": [],
  "version": "current",
  "frontMatter": {
    "title": "3.  9. Gizi"
  },
  "sidebar": "tutorialSidebar",
  "previous": {
    "title": "3.  8. Anestesi dan Bedah",
    "permalink": "/docs/pkp/8"
  },
  "next": {
    "title": "Akreditasi Klinik",
    "permalink": "/docs/"
  }
}